odoo/addons/sale_order_warn_message/README.rst
odoo/addons/sale_order_warn_message/__init__.py
odoo/addons/sale_order_warn_message/__manifest__.py
odoo/addons/sale_order_warn_message/i18n/es.po
odoo/addons/sale_order_warn_message/i18n/it.po
odoo/addons/sale_order_warn_message/i18n/sale_order_warn_message.pot
odoo/addons/sale_order_warn_message/models/__init__.py
odoo/addons/sale_order_warn_message/models/sale_order.py
odoo/addons/sale_order_warn_message/readme/CONTRIBUTORS.rst
odoo/addons/sale_order_warn_message/readme/DESCRIPTION.rst
odoo/addons/sale_order_warn_message/static/description/icon.png
odoo/addons/sale_order_warn_message/static/description/index.html
odoo/addons/sale_order_warn_message/tests/__init__.py
odoo/addons/sale_order_warn_message/tests/test_sale_order_warn_message.py
odoo/addons/sale_order_warn_message/views/sale_order.xml
odoo14_addon_sale_order_warn_message-14.0.1.1.1.dev10.dist-info/METADATA
odoo14_addon_sale_order_warn_message-14.0.1.1.1.dev10.dist-info/WHEEL
odoo14_addon_sale_order_warn_message-14.0.1.1.1.dev10.dist-info/top_level.txt
odoo14_addon_sale_order_warn_message-14.0.1.1.1.dev10.dist-info/RECORD
